exception_details/__init__.py
exception_details/_version.py
exception_details/exception_details.py
exception_details/test.py
exception_details-0.0.3.dist-info/licenses/LICENSE
exception_details-0.0.3.dist-info/METADATA
exception_details-0.0.3.dist-info/WHEEL
exception_details-0.0.3.dist-info/top_level.txt
exception_details-0.0.3.dist-info/RECORD
